rnd_pcw_poly/__init__.py
rnd_pcw_poly/pcw_fn.py
rnd_pcw_poly-0.2.0.dist-info/LICENSE
rnd_pcw_poly-0.2.0.dist-info/METADATA
rnd_pcw_poly-0.2.0.dist-info/WHEEL
rnd_pcw_poly-0.2.0.dist-info/RECORD
