Metadata-Version: 2.1
Name: rnd-pcw-poly
Version: 0.2.0
Summary: Generate random piecewise polynomials
Home-page: https://github.com/SV-97/rnd-pcw-poly
Author: Stefan Volz
Author-email: volzstefan97@googlemail.com
Requires-Python: >=3.10,<4.0
Classifier: License :: OSI Approved :: MIT License
Classifier: Operating System :: OS Independent
Classifier: Programming Language :: Python :: 3
Classifier: Programming Language :: Python :: 3.10
Classifier: Programming Language :: Python :: 3.11
Classifier: Programming Language :: Python :: 3
Classifier: Topic :: Scientific/Engineering :: Mathematics
Requires-Dist: matplotlib (>=3.7.1,<4.0.0)
Requires-Dist: numpy (>=1.24.2,<2.0.0)
Requires-Dist: random-partition-py (==0.2.0)
Project-URL: Repository, https://github.com/SV-97/rnd-pcw-poly
